HISTORY.rst
LICENSE
MANIFEST.in
NOTICE
README.rst
setup.py
requests_netdna/__init__.py
requests_netdna/_oauth.py
requests_netdna/api.py
requests_netdna/async.py
requests_netdna/auth.py
requests_netdna/certs.py
requests_netdna/compat.py
requests_netdna/cookies.py
requests_netdna/defaults.py
requests_netdna/exceptions.py
requests_netdna/hooks.py
requests_netdna/models.py
requests_netdna/safe_mode.py
requests_netdna/sessions.py
requests_netdna/status_codes.py
requests_netdna/structures.py
requests_netdna/utils.py
requests_netdna.egg-info/PKG-INFO
requests_netdna.egg-info/SOURCES.txt
requests_netdna.egg-info/dependency_links.txt
requests_netdna.egg-info/requires.txt
requests_netdna.egg-info/top_level.txt
requests_netdna/packages/__init__.py
requests_netdna/packages/chardet/__init__.py
requests_netdna/packages/chardet/big5freq.py
requests_netdna/packages/chardet/big5prober.py
requests_netdna/packages/chardet/chardistribution.py
requests_netdna/packages/chardet/charsetgroupprober.py
requests_netdna/packages/chardet/charsetprober.py
requests_netdna/packages/chardet/codingstatemachine.py
requests_netdna/packages/chardet/constants.py
requests_netdna/packages/chardet/escprober.py
requests_netdna/packages/chardet/escsm.py
requests_netdna/packages/chardet/eucjpprober.py
requests_netdna/packages/chardet/euckrfreq.py
requests_netdna/packages/chardet/euckrprober.py
requests_netdna/packages/chardet/euctwfreq.py
requests_netdna/packages/chardet/euctwprober.py
requests_netdna/packages/chardet/gb2312freq.py
requests_netdna/packages/chardet/gb2312prober.py
requests_netdna/packages/chardet/hebrewprober.py
requests_netdna/packages/chardet/jisfreq.py
requests_netdna/packages/chardet/jpcntx.py
requests_netdna/packages/chardet/langbulgarianmodel.py
requests_netdna/packages/chardet/langcyrillicmodel.py
requests_netdna/packages/chardet/langgreekmodel.py
requests_netdna/packages/chardet/langhebrewmodel.py
requests_netdna/packages/chardet/langhungarianmodel.py
requests_netdna/packages/chardet/langthaimodel.py
requests_netdna/packages/chardet/latin1prober.py
requests_netdna/packages/chardet/mbcharsetprober.py
requests_netdna/packages/chardet/mbcsgroupprober.py
