Metadata-Version: 1.0
Name: requests-netdna
Version: 0.13.6
Summary: Python HTTP for Humans.
Home-page: http://python-requests.org
Author: Kenneth Reitz
Author-email: me@kennethreitz.com
License: Copyright (c) 2012 Kenneth Reitz.
